SuperconGAN/__init__.py
SuperconGAN/data.py
SuperconGAN/model.py
SupeconGAN_RajeevAtla-0.0.1.dist-info/LICENSE
SupeconGAN_RajeevAtla-0.0.1.dist-info/METADATA
SupeconGAN_RajeevAtla-0.0.1.dist-info/WHEEL
SupeconGAN_RajeevAtla-0.0.1.dist-info/top_level.txt
SupeconGAN_RajeevAtla-0.0.1.dist-info/RECORD
