Metadata-Version: 2.1
Name: SupeconGAN-RajeevAtla
Version: 0.0.1
Summary: GAN trained on superconductivity data
Home-page: https://github.com/RajeevAtla/SuperconGAN
Author: Rajeev Atla
Author-email: rajeev@rajeevatla.com
License: UNKNOWN
Platform: UNKNOWN
Classifier: Programming Language :: Python :: 3
Classifier: License :: OSI Approved :: MIT License
Classifier: Operating System :: OS Independent
Requires-Python: >=3.6
